sshcopyid/__init__.py
sshcopyid/cli.py
sshcopyid-0.0.6.dist-info/LICENSE
sshcopyid-0.0.6.dist-info/METADATA
sshcopyid-0.0.6.dist-info/WHEEL
sshcopyid-0.0.6.dist-info/entry_points.txt
sshcopyid-0.0.6.dist-info/top_level.txt
sshcopyid-0.0.6.dist-info/RECORD
