Metadata-Version: 2.1
Name: sshcopyid
Version: 0.0.6
Summary: A Windows-friendly replacement for the Linux ssh-copy-id tool.
Home-page: https://github.com/meena-erian/ssh-copy-id
Author: Meena (Menas) Erian
Author-email: menas@portacode.com
License: MIT
Platform: UNKNOWN
Classifier: Environment :: Win32 (MS Windows)
Classifier: License :: OSI Approved :: MIT License
Classifier: Operating System :: Microsoft :: Windows
Classifier: Programming Language :: Python :: 3.6
Classifier: Programming Language :: Python :: 3
Classifier: Topic :: System :: Networking
Requires-Python: >=3.6
License-File: LICENSE
